EPWpy/EPWpy.py
EPWpy/EPWpy_analysis.py
EPWpy/EPWpy_prepare.py
EPWpy/EPWpy_run.py
EPWpy/Logo.py
EPWpy/__init__.py
EPWpy/polaron.py
EPWpy/Abinit/Abinit_util.py
EPWpy/Abinit/EPWpy_Abinit.py
EPWpy/Abinit/__init__.py
EPWpy/Abinit/set_Abinit.py
EPWpy/Abinit/write_Abinit.py
EPWpy/BGW/BGW_init.py
EPWpy/BGW/BGW_set_links.py
EPWpy/BGW/EPWpy_BGW.py
EPWpy/BGW/__init__.py
EPWpy/BGW/write_BGW.py
EPWpy/BGW/write_QE_BGW.py
EPWpy/QE/EPWpy_QE.py
EPWpy/QE/PH_util.py
EPWpy/QE/PW_util.py
EPWpy/QE/PWscf_out.py
EPWpy/QE/__init__.py
EPWpy/QE/auto_wannier.py
EPWpy/QE/set_QE.py
EPWpy/QE/write_QE.py
EPWpy/default/__init__.py
EPWpy/default/code_loc.py
EPWpy/default/default.py
EPWpy/default/default_colors.py
EPWpy/default/set_default.py
EPWpy/error_handling/__init__.py
EPWpy/error_handling/error_handler.py
EPWpy/flow/__init__.py
EPWpy/flow/transport.py
EPWpy/plotting/__init__.py
EPWpy/plotting/default_param.py
EPWpy/plotting/default_params.py
EPWpy/plotting/plot_bands.py
EPWpy/plotting/plot_g.py
EPWpy/plotting/plot_polaron.py
EPWpy/plotting/plot_supercond.py
EPWpy/plotting/plot_wannier.py
EPWpy/structure/__init__.py
EPWpy/structure/lattice.py
EPWpy/structure/position_atoms.py
EPWpy/structure/structure.py
EPWpy/utilities/BGW_util.py
EPWpy/utilities/Band.py
EPWpy/utilities/EPW_util.py
EPWpy/utilities/__init__.py
EPWpy/utilities/check_util.py
EPWpy/utilities/constants.py
EPWpy/utilities/display_struct.py
EPWpy/utilities/epw_pp.py
EPWpy/utilities/k_gen.py
EPWpy/utilities/kramers_kronig.py
EPWpy/utilities/kronig_penny.py
EPWpy/utilities/parse.py
EPWpy/utilities/printing.py
EPWpy/utilities/read_QE.py
EPWpy/utilities/save_state.py
EPWpy/utilities/set_files.py
EPWpy_basic-1.0.dev1.dist-info/METADATA
EPWpy_basic-1.0.dev1.dist-info/WHEEL
EPWpy_basic-1.0.dev1.dist-info/top_level.txt
EPWpy_basic-1.0.dev1.dist-info/RECORD
